{
    "specification": [
        {
            "GENERAL FEATURES": {
                "Brand": "BQ",
                "Handset Color": "Green",
                "In the Box": "Mobile",
                "Model Name": "K26",
                "SIM Size": "Normal SIM",
                "SIM Type": "Dual Sim",
                "Touch Screen": "No"
            }
        },
        {
            "Camera": {
                "Primary Camera": "Yes, 1.3 Megapixel"
            }
        },
        {
            "Internet & Connectivity": {
                "3G": "No",
                "Audio Jack": "3.5mm",
                "HDMI Port": "No",
                "USB Connectivity": "Yes, micro USB",
                "Wifi": "No"
            }
        },
        {
            "Warranty": {
                "Warranty Summary": "1 Year Manufacturer Warranty"
            }
        },
        {
            "Dimensions": {
                "Size": "51.9x120.6x11.8 mm"
            }
        },
        {
            "Display": {
                "Resolution": "240 x 320 Pixels",
                "Size": "2.6 Inches",
                "Type": "QVGA"
            }
        },
        {
            "Battery": {
                "Type": "Li-Ion, 1200 mAh"
            }
        },
        {
            "Memory and Storage": {
                "Expandable Memory": "microSD, upto 16 GB",
                "Internal": "64 MB"
            }
        },
        {
            "Platform": {
                "Processor": "MTK6260D"
            }
        }
    ]
}