{
    "specification": [
        {
            "GENERAL FEATURES": {
                "Brand": "Gionee",
                "Call Features": "Loudspeaker",
                "Form": "Bar",
                "Handset Color": "Black",
                "Model ID": "M3",
                "SIM Size": "Micro SIM",
                "SIM Type": "Dual Sim, GSM + WCDMA",
                "Touch Screen": "Yes"
            }
        },
        {
            "Multimedia": {
                "FM": "Yes",
                "Music Player": "Yes, Supports MP3",
                "Sound Enhancement": "Dual Noise Cancellation, DTS Sounds",
                "Video Player": "Yes, Full HD"
            }
        },
        {
            "Camera": {
                "Flash": "LED",
                "HD Recording": "HD, Full HD",
                "Other Camera Features": "Auto Focus",
                "Primary Camera": "Yes, 8 Megapixel",
                "Secondary Camera": "Yes, 2 Megapixel",
                "Video Recording": "Yes, 1920 x 1080"
            }
        },
        {
            "Internet & Connectivity": {
                "3G": "Yes",
                "Bluetooth": "Yes",
                "Internet Features": "Email",
                "Navigation Technology": "with Google Maps",
                "Preinstalled Browser": "Android",
                "Wifi": "Yes"
            }
        },
        {
            "Other Features": {
                "Additional Features": "OTG Reverse Charge, OTG Support, Double Tap Wakeup",
                "Call Memory": "Yes",
                "Important Apps": "HotKnot, Black Screen Gesture Control",
                "Phone Book Memory": "Yes",
                "SMS Memory": "Yes",
                "Sensors": "Light Sensor, Compass, Acceleration Sensor, Proximity Sensor"
            }
        },
        {
            "Warranty": {
                "Warranty Summary": "1 year manufacturer warranty for Phone and 6 months warranty for in the box accessories"
            }
        },
        {
            "Dimensions": {
                "Size": "71.45x144.5x10.4 mm",
                "Weight": "180.3 g"
            }
        },
        {
            "Display": {
                "Other Display Features": "IPS Display, Multi-touch",
                "Resolution": "HD, 1280 x 720 Pixels",
                "Size": "5 Inches"
            }
        },
        {
            "Battery": {
                "Standby Time": "787 hrs (2G)",
                "Talk Time": "33 hrs (2G)",
                "Type": "5000 mAh"
            }
        },
        {
            "Memory and Storage": {
                "Expandable Memory": "microSD, upto 128 GB",
                "Internal": "8 GB",
                "Memory": "1 GB RAM, 8 GB ROM"
            }
        },
        {
            "Platform": {
                "OS": "Android v4.4 (KitKat)",
                "Operating Freq": "GSM - 850, 900, 1800, 1900; WCDMA - 2100",
                "Processor": "1.3 GHz + MT6582V/W, Quad Core"
            }
        }
    ]
}