{
    "specification": [
        {
            "GENERAL FEATURES": {
                "Brand": "HTC",
                "Handset Color": "Red",
                "In the Box": "Handset, Charging Adapter, Data Cable, Sim Ejector",
                "Model Name": "ONE E8 (M8Sd)",
                "SIM Type": "Dual Sim",
                "Touch Screen": "Yes"
            }
        },
        {
            "Display": {
                "Resolution": "1920 x 1080 Pixels",
                "Size": "5 Inches"
            }
        },
        {
            "Battery": {
                "Type": "Li-Po, 2600 mAh"
            }
        },
        {
            "Memory and Storage": {
                "Internal": "16 GB"
            }
        }
    ]
}