{
    "specification": [
        {
            "GENERAL FEATURES": {
                "Brand": "Lava",
                "Business Features": "Document Viewer, Office Suite",
                "Call Features": "Conference Call, Loudspeaker",
                "Form": "Bar",
                "Handset Color": "White",
                "In the Box": "Ear Phone, USB Cable, Phone, Battery, Charger, User Manual, Flip Cover, Screen Guard",
                "Model ID": "Fuel 20",
                "Model Name": "Iris",
                "SIM Type": "Dual Sim, GSM + GSM, (Dual Standby)",
                "Touch Screen": "Yes, Capacitive"
            }
        },
        {
            "Multimedia": {
                "FM": "Yes, with Recording",
                "Music Player": "Yes, Supports AMR, eAAC+, MIDI, MP3, WAV, WMA, AAC+, AAC",
                "Ringtone": "WMA, WAV, MIDI, MP3, AAC, AMR",
                "Video Player": "Yes, Supports WMA, 3GP, MPEG4, AVI, HD"
            }
        },
        {
            "Camera": {
                "Flash": "LED",
                "HD Recording": "HD",
                "Other Camera Features": "HDR, Panorama",
                "Primary Camera": "Yes, 5 Megapixel",
                "Secondary Camera": "Yes, 0.3 Megapixel",
                "Video Recording": "Yes, 1280 x 720",
                "Zoom": "Digital Zoom"
            }
        },
        {
            "Internet & Connectivity": {
                "Audio Jack": "3.5 mm",
                "Bluetooth": "Yes, v4",
                "EDGE": "Yes",
                "GPRS": "Yes",
                "Internet Features": "Email",
                "Navigation Technology": "A-GPS, with Google Maps",
                "Preinstalled Browser": "Android, Google Chrome, Opera",
                "Tethering": "USB",
                "USB Connectivity": "Yes",
                "Wifi": "Yes, 802.11 b/g/n"
            }
        },
        {
            "Other Features": {
                "Additional Features": "To Do List, News and Weather, Language Translator, Hands-free, Call Recorder, 13 hrs of Non-stop Video Streaming",
                "Call Memory": "Yes",
                "Important Apps": "Google Talk, YouTube, Gmail, Google Search, Google Play",
                "Phone Book Memory": "Yes",
                "SMS Memory": "Yes",
                "Sensors": "Proximity Sensor, Accelerometer, Ambient Light Sensor"
            }
        },
        {
            "Warranty": {
                "Warranty Summary": "1 year manufacturer warranty for Phone and 6 months warranty for in the box accessories"
            }
        },
        {
            "Dimensions": {
                "Size": "74x145.6x10.8 mm"
            }
        },
        {
            "Display": {
                "Color": "16.7 M",
                "Other Display Features": "Multi-point Touch",
                "Resolution": "Others, 854 x 480 Pixels",
                "Size": "5 Inches",
                "Type": "LCD"
            }
        },
        {
            "Battery": {
                "Talk Time": "42 hrs (2G)",
                "Type": "Li-Polymer, 4400 mAh"
            }
        },
        {
            "Memory and Storage": {
                "Expandable Memory": "microSD, upto 32 GB",
                "Internal": "4",
                "Memory": "512 MB RAM, 4 GB ROM"
            }
        },
        {
            "Platform": {
                "OS": "Android v4.4 (KitKat)",
                "Operating Freq": "GSM - 900, 1800",
                "Processor": "1.3 GHz, Dual Core",
                "User Interface": "Standard Android"
            }
        }
    ]
}