{
    "specification": [
        {
            "GENERAL FEATURES": {
                "Brand": "LG",
                "Handset Color": "Black||White",
                "In the Box": "Mobile, Battery, Earphone, USB Cable, Manual",
                "Model Name": "L Fino D295",
                "SIM Size": "Micro SIM",
                "SIM Type": "Dual Sim",
                "Touch Screen": "Yes"
            }
        },
        {
            "Camera": {
                "HD Recording": "HD",
                "Primary Camera": "8 Megapixel",
                "Secondary Camera": "0.3 Megapixel"
            }
        },
        {
            "Internet & Connectivity": {
                "3G": "Yes",
                "Audio Jack": "3.5mm",
                "USB Connectivity": "Yes, micro USB",
                "Wifi": "Yes"
            }
        },
        {
            "Other Features": {
                "Sensors": "Proximity, Accelerometer"
            }
        },
        {
            "Display": {
                "Resolution": "800 x 480 Pixels",
                "Size": "4.5 Inches",
                "Type": "IPS TFT Capacitive"
            }
        },
        {
            "Warranty": {
                "Warranty Summary": "1 Year LG India Warranty"
            }
        },
        {
            "Battery": {
                "Type": "Li-ion, 1900 mAh"
            }
        },
        {
            "Memory and Storage": {
                "Expandable Memory": "microSD, upto 32 GB",
                "Internal": "4 GB",
                "Memory": "1 GB RAM"
            }
        },
        {
            "Platform": {
                "OS": "Android v4.4 (KitKat)",
                "Processor": "1.2 GHz + Qualcomm, Quad Core"
            }
        }
    ]
}