{
    "specification": [
        {
            "GENERAL FEATURES": {
                "Brand": "Maxx",
                "Handset Color": "Black & Red",
                "In the Box": "Manual, Handset, Battery, Headphone, Charger",
                "Model Name": "MX468-sleek",
                "SIM Type": "Dual Sim",
                "Touch Screen": "No"
            }
        },
        {
            "Camera": {
                "Primary Camera": "No"
            }
        },
        {
            "Internet & Connectivity": {
                "Audio Jack": "3.5 mm",
                "USB Connectivity": "Yes"
            }
        },
        {
            "Warranty": {
                "Warranty Summary": "1 year manufacturer warranty for Phone and 6 months warranty for in the box accessories"
            }
        },
        {
            "Dimensions": {
                "Size": "52.9x123.7x10.7 mm"
            }
        },
        {
            "Display": {
                "Resolution": "240 x 320 Pixels",
                "Size": "2.4 Inches"
            }
        },
        {
            "Battery": {
                "Type": "Li-Ion, 1500 mAh"
            }
        },
        {
            "Memory and Storage": {
                "Expandable Memory": "microSD, upto 8 GB",
                "Internal": "10 KB"
            }
        }
    ]
}