{
    "specification": [
        {
            "GENERAL FEATURES": {
                "Brand": "Micromax",
                "Handset Color": "Black",
                "In the Box": "Handset, USB Cable, Charger, User Guide, Warranty Card, Battery, Handsfree",
                "Model Name": "X096",
                "SIM Size": "Micro SIM",
                "SIM Type": "Dual Sim",
                "Touch Screen": "No"
            }
        },
        {
            "Camera": {
                "Primary Camera": "Yes, 0.08 Megapixel"
            }
        },
        {
            "Internet & Connectivity": {
                "3G": "No",
                "USB Connectivity": "Yes",
                "Wifi": "No"
            }
        },
        {
            "Warranty": {
                "Warranty Summary": "1 year manufacturer warranty for Phone and 6 months warranty for in the box accessories"
            }
        },
        {
            "Dimensions": {
                "Size": "51.5x116x15.4 mm"
            }
        },
        {
            "Display": {
                "Resolution": "176 x 220 Pixels",
                "Size": "4.5 Inches",
                "Type": "TFT"
            }
        },
        {
            "Battery": {
                "Type": "Li-Ion, 1000 mAh"
            }
        },
        {
            "Memory and Storage": {
                "Expandable Memory": "microSD, upto 8 GB",
                "Internal": "0"
            }
        }
    ]
}