{
    "specification": [
        {
            "GENERAL FEATURES": {
                "Brand": "Panasonic",
                "Handset Color": "Red",
                "In the Box": "1 Handset(Including Battery), 1 Charger, 1 USB Charger, 1 USB Cable, 1 Ear Phone, 1 Quick Start Guide, 1 Warranty Card",
                "Model Name": "T41",
                "SIM Size": "Micro SIM",
                "SIM Type": "Dual Sim",
                "Touch Screen": "Yes"
            }
        },
        {
            "Camera": {
                "Primary Camera": "5 Megapixel",
                "Secondary Camera": "0.3 Megapixel"
            }
        },
        {
            "Internet & Connectivity": {
                "3G": "Yes",
                "Wifi": "Yes"
            }
        },
        {
            "Other Features": {
                "Sensors": "G-Sensor, Proximity Sensor, Light Sensor"
            }
        },
        {
            "Display": {
                "Resolution": "480 x 854 Pixels",
                "Size": "4.5 Inches",
                "Type": "IPS"
            }
        },
        {
            "Battery": {
                "Type": "Li-Po, 1650 mAh"
            }
        },
        {
            "Memory and Storage": {
                "Expandable Memory": "microSD, upto 32 GB",
                "Internal": "4 GB",
                "Memory": "512 MB RAM"
            }
        },
        {
            "Platform": {
                "OS": "Android v4.4 (KitKat)",
                "Processor": "1.3 GHz + 1.3 GHZ Quad Core Processor, Quad Core"
            }
        }
    ]
}