{
    "specification": [
        {
            "GENERAL FEATURES": {
                "Brand": "Sansui",
                "Handset Color": "Black",
                "In the Box": "Mobile",
                "Model Name": "SA50",
                "SIM Type": "Dual Sim",
                "Touch Screen": "Yes"
            }
        },
        {
            "Camera": {
                "Primary Camera": "Yes, 2 Megapixel"
            }
        },
        {
            "Internet & Connectivity": {
                "3G": "No",
                "USB Connectivity": "Yes",
                "Wifi": "Yes"
            }
        },
        {
            "Display": {
                "Resolution": "480 x 800 Pixels",
                "Size": "5 Inches",
                "Type": "5 inch Capacitive Touchscreen"
            }
        },
        {
            "Battery": {
                "Type": "Li-Ion, 1800 mAh"
            }
        },
        {
            "Memory and Storage": {
                "Expandable Memory": "microSD, upto 16 GB",
                "Internal": "512 MB"
            }
        },
        {
            "Platform": {
                "OS": "Android"
            }
        }
    ]
}