{
    "specification": [
        {
            "GENERAL FEATURES": {
                "Brand": "Videocon",
                "Handset Color": "White",
                "In the Box": "Handset, Protective Pouch, Service Center Directory, Data Cable, User Manual, Charger, Warranty Card, Battery, Headset",
                "Model Name": "A55HD",
                "SIM Type": "Dual Sim",
                "Touch Screen": "Yes"
            }
        },
        {
            "Camera": {
                "HD Recording": "HD, Full HD",
                "Primary Camera": "Yes, 8 Megapixel",
                "Secondary Camera": "3.2 Megapixel"
            }
        },
        {
            "Internet & Connectivity": {
                "3G": "Yes",
                "Audio Jack": "3.5 mm",
                "USB Connectivity": "Yes",
                "Wifi": "Yes"
            }
        },
        {
            "Display": {
                "Resolution": "1280 x 720 Pixels",
                "Size": "5 Inches"
            }
        },
        {
            "Battery": {
                "Type": "Li-Ion, 2000 mAh"
            }
        },
        {
            "Memory and Storage": {
                "Expandable Memory": "microSD, upto 32 GB",
                "Internal": "4 GB",
                "Memory": "1 GB RAM"
            }
        },
        {
            "Platform": {
                "OS": "Android v4.2.2 (Jelly Bean)",
                "Processor": "1.2 GHz + Quadcore, Quad Core"
            }
        }
    ]
}