{
    "specification": [
        {
            "GENERAL FEATURES": {
                "Brand": "Vox",
                "Handset Color": "Black",
                "In the Box": "Mobile, Charger, Earphone, User Manual, Bluetooth Headset",
                "Model Name": "V-3100-BT",
                "SIM Size": "Full Size SIM",
                "SIM Type": "Triple Sim",
                "Touch Screen": "No"
            }
        },
        {
            "Camera": {
                "Primary Camera": "1.3 Megapixel"
            }
        },
        {
            "Internet & Connectivity": {
                "3G": "No",
                "Audio Jack": "3.5 mm",
                "HDMI Port": "No",
                "USB Connectivity": "Yes, micro USB",
                "Wifi": "No"
            }
        },
        {
            "Warranty": {
                "Covered in Warranty": "Warranty of the product is limited to manufacturing defects only",
                "Warranty Service Type": "Off Site Service. Customer needs to call centralized service center",
                "Warranty Summary": "Six Months Manufacturer Warranty"
            }
        },
        {
            "Dimensions": {
                "Size": "45x100x12 mm"
            }
        },
        {
            "Display": {
                "Resolution": "128 x 160 Pixels",
                "Size": "1.8 Inches",
                "Type": "TFT LCD"
            }
        },
        {
            "Battery": {
                "Type": "Li-ion, 800 mAh"
            }
        },
        {
            "Memory and Storage": {
                "Expandable Memory": "microSD, upto 8 GB",
                "Internal": "0"
            }
        },
        {
            "Platform": {
                "OS": "Symbian"
            }
        }
    ]
}